{
  "db_name": "PostgreSQL",
  "query": "\n        INSERT INTO route_proposals (route_id, geometry, comment, created_by)\n        VALUES ($1, $2, $3, $4)\n        RETURNING *\n        ",
  "describe": {
    "columns": [
      {
        "ordinal": 0,
        "name": "id",
        "type_info": "Uuid"
      },
      {
        "ordinal": 1,
        "name": "route_id",
        "type_info": "Uuid"
      },
      {
        "ordinal": 2,
        "name": "geometry",
        "type_info": "Jsonb"
      },
      {
        "ordinal": 3,
        "name": "comment",
        "type_info": "Text"
      },
      {
        "ordinal": 4,
        "name": "status",
        "type_info": "Text"
      },
      {
        "ordinal": 5,
        "name": "created_by",
        "type_info": "Uuid"
      },
      {
        "ordinal": 6,
        "name": "created_at",
        "type_info": "Timestamptz"
      },
      {
        "ordinal": 7,
        "name": "updated_at",
        "type_info": "Timestamptz"
      }
    ],
    "parameters": {
      "Left": [
        "Uuid",
        "Jsonb",
        "Text",
        "Uuid"
      ]
    },
    "nullable": [
      false,
      false,
      false,
      false,
      false,
      true,
      false,
      false
    ]
  },
  "hash": "d2eb8448f09e9c9151a4671e7a34161735679c76289850becb5831ebe289a9d6"
}
